README.md
setup.py
pyalsi/__init__.py
pyalsi/colors.py
pyalsi/logos.py
pyalsi/window_managers.py
pyalsi.egg-info/PKG-INFO
pyalsi.egg-info/SOURCES.txt
pyalsi.egg-info/dependency_links.txt
pyalsi.egg-info/entry_points.txt
pyalsi.egg-info/requires.txt
pyalsi.egg-info/top_level.txt
pyalsi/hardware/__init__.py
pyalsi/hardware/cpu/__init__.py
pyalsi/hardware/cpu/cpu.py
pyalsi/hardware/disks/__init__.py
pyalsi/hardware/disks/disk.py
pyalsi/hardware/ram/__init__.py
pyalsi/hardware/ram/ram.py
pyalsi/hardware/vga/__init__.py
pyalsi/hardware/vga/vga.py
pyalsi/system/__init__.py
pyalsi/system/system.py
pyalsi/tests/__init__.py
pyalsi/tests/base_test.py
pyalsi/tests/arch/__init__.py
pyalsi/tests/arch/test_arch_commands.py
pyalsi/tests/common/__init__.py
pyalsi/tests/common/test_common_flags.py
pyalsi/tests/debian/__init__.py
pyalsi/tests/debian/test_debian_commands.py
pyalsi/tests/fedora/__init__.py
pyalsi/tests/mock_classes/__init__.py
pyalsi/tests/mock_classes/os_popen.py
pyalsi/tests/ubuntu/__init__.py
pyalsi/tests/unit/__init__.py
pyalsi/tests/unit/hardware/__init__.py
pyalsi/tests/unit/hardware/test_disk.py
pyalsi/tests/unit/hardware/test_vga.py
pyalsi/tests/unit/utils/__init__.py
pyalsi/tests/unit/utils/test_sanity_checks.py
pyalsi/tests/unit/utils/test_utils.py
pyalsi/utils/__init__.py
pyalsi/utils/strings.py
pyalsi/utils/types.py